yadisk_shadow/__init__.py
yadisk_shadow/yadisk_shadow.py
yadisk_shadow-0.9.0.dist-info/METADATA
yadisk_shadow-0.9.0.dist-info/WHEEL
yadisk_shadow-0.9.0.dist-info/entry_points.txt
yadisk_shadow-0.9.0.dist-info/licenses/LICENSE
yadisk_shadow-0.9.0.dist-info/RECORD
