Metadata-Version: 2.1
Name: yadisk-shadow
Version: 0.9.0
Summary: Yandex Disk Shared Folders Metadata & Files Downloader
Project-URL: Homepage, https://github.com/regnveig/yadisk-shadow
Project-URL: Bug Tracker, https://github.com/regnveig/yadisk-shadow/issues
Author-email: Emil Viesná <regnveig@yandex.ru>
License-File: LICENSE
Keywords: disk,downloader,shared,yandex
Classifier: Development Status :: 2 - Pre-Alpha
Classifier: Environment :: Console
Classifier: License :: OSI Approved :: GNU General Public License v3 (GPLv3)
Classifier: Natural Language :: English
Classifier: Operating System :: OS Independent
Classifier: Programming Language :: Python :: 3.8
Classifier: Programming Language :: Python :: 3.9
Classifier: Programming Language :: Python :: 3.10
Requires-Python: >=3.8
Requires-Dist: requests
Requires-Dist: tqdm
